{
  "groups": [
    {
      "name": "ai.model",
      "type": "com.shier.shierbi.config.AiModelConfig",
      "sourceType": "com.shier.shierbi.config.AiModelConfig"
    },
    {
      "name": "spring.redis",
      "type": "com.shier.shierbi.config.RedissonConfig",
      "sourceType": "com.shier.shierbi.config.RedissonConfig"
    }
  ],
  "properties": [
    {
      "name": "ai.model.model-id",
      "type": "java.lang.Long",
      "description": "模型id",
      "sourceType": "com.shier.shierbi.config.AiModelConfig"
    },
    {
      "name": "spring.redis.database",
      "type": "java.lang.Integer",
      "sourceType": "com.shier.shierbi.config.RedissonConfig"
    },
    {
      "name": "spring.redis.host",
      "type": "java.lang.String",
      "sourceType": "com.shier.shierbi.config.RedissonConfig"
    },
    {
      "name": "spring.redis.password",
      "type": "java.lang.String",
      "sourceType": "com.shier.shierbi.config.RedissonConfig"
    },
    {
      "name": "spring.redis.port",
      "type": "java.lang.Integer",
      "sourceType": "com.shier.shierbi.config.RedissonConfig"
    }
  ],
  "hints": []
}